odoo/addons/pos_hide_banknote_button/README.rst
odoo/addons/pos_hide_banknote_button/__init__.py
odoo/addons/pos_hide_banknote_button/__manifest__.py
odoo/addons/pos_hide_banknote_button/i18n/es.po
odoo/addons/pos_hide_banknote_button/i18n/fr.po
odoo/addons/pos_hide_banknote_button/i18n/pos_hide_banknote_button.pot
odoo/addons/pos_hide_banknote_button/readme/CONTRIBUTORS.rst
odoo/addons/pos_hide_banknote_button/readme/DESCRIPTION.rst
odoo/addons/pos_hide_banknote_button/static/description/after.png
odoo/addons/pos_hide_banknote_button/static/description/before.png
odoo/addons/pos_hide_banknote_button/static/description/icon.png
odoo/addons/pos_hide_banknote_button/static/description/index.html
odoo/addons/pos_hide_banknote_button/static/src/css/pos_hide_banknote_button.css
odoo/addons/pos_hide_banknote_button/views/assets.xml
odoo12_addon_pos_hide_banknote_button-12.0.1.0.1.dist-info/METADATA
odoo12_addon_pos_hide_banknote_button-12.0.1.0.1.dist-info/WHEEL
odoo12_addon_pos_hide_banknote_button-12.0.1.0.1.dist-info/top_level.txt
odoo12_addon_pos_hide_banknote_button-12.0.1.0.1.dist-info/RECORD
